st_hotfix/__init__.py
st_hotfix/__main__.py
st_hotfix/cdn.py
st_hotfix/util.py
streamlit_hotfix-0.1.1.dist-info/LICENSE
streamlit_hotfix-0.1.1.dist-info/METADATA
streamlit_hotfix-0.1.1.dist-info/WHEEL
streamlit_hotfix-0.1.1.dist-info/entry_points.txt
streamlit_hotfix-0.1.1.dist-info/RECORD
